openai_function_call/__init__.py
openai_function_call/dsl/__init__.py
openai_function_call/dsl/completion.py
openai_function_call/dsl/messages/__init__.py
openai_function_call/dsl/messages/base.py
openai_function_call/dsl/messages/messages.py
openai_function_call/dsl/messages/user.py
openai_function_call/dsl/multitask.py
openai_function_call/function_calls.py
openai_function_call/patch.py
openai_function_call-0.2.6.dist-info/LICENSE
openai_function_call-0.2.6.dist-info/METADATA
openai_function_call-0.2.6.dist-info/WHEEL
openai_function_call-0.2.6.dist-info/RECORD
