Metadata-Version: 2.1
Name: openai-function-call
Version: 0.2.6
Summary: Helper functions that allow us to improve openai's function_call ergonomics
Home-page: https://github.com/jxnl/openai_function_call
License: MIT
Author: Jason
Author-email: jason@jxnl.co
Requires-Python: >=3.9,<4.0
Classifier: License :: OSI Approved :: MIT License
Classifier: Programming Language :: Python :: 3
Classifier: Programming Language :: Python :: 3.9
Classifier: Programming Language :: Python :: 3.10
Classifier: Programming Language :: Python :: 3.11
Requires-Dist: openai (>=0.27.8,<0.28.0)
Requires-Dist: pydantic (>=2.0.2,<3.0.0)
Project-URL: Repository, https://github.com/jxnl/openai_function_call
